basic_repo_template/__init__.py
basic_repo_template/__main__.py
basic_repo_template/basic_repo_template.py
basic_repo_template/test_test.py
basic_repo_template/system/__init__.py
basic_repo_template/system/default_paths.py
basic_repo_template/system/logging_configuration.py
basic_repo_template-2023.1.1004.dist-info/entry_points.txt
basic_repo_template-2023.1.1004.dist-info/LICENSE
basic_repo_template-2023.1.1004.dist-info/WHEEL
basic_repo_template-2023.1.1004.dist-info/METADATA
basic_repo_template-2023.1.1004.dist-info/RECORD
