Metadata-Version: 2.1
Name: basic_repo_template
Version: 2023.1.1004
Summary: Basic template of a python repository
Keywords: basic,template,python,repository
Author-email: Skelly FreeMoCap <info@freemocap.org>
Requires-Python: >=3.8
Classifier: License :: OSI Approved :: GNU Affero General Public License v3 or later (AGPLv3+)
Classifier: Programming Language :: Python
Classifier: Programming Language :: Python :: 3
Requires-Dist: pytest
Requires-Dist: black ; extra == "dev"
Requires-Dist: bumpver ; extra == "dev"
Requires-Dist: isort ; extra == "dev"
Requires-Dist: pip-tools ; extra == "dev"
Requires-Dist: pytest ; extra == "dev"
Provides-Extra: dev
